django_excel_viewset/__init__.py
django_excel_viewset/excel_writer/__init__.py
django_excel_viewset/excel_writer/creator.py
django_excel_viewset/responses.py
django_excel_viewset/serializers.py
django_excel_viewset/settings.py
django_excel_viewset/views.py
django_excel_viewset-0.0.1.dist-info/LICENSE
django_excel_viewset-0.0.1.dist-info/METADATA
django_excel_viewset-0.0.1.dist-info/WHEEL
django_excel_viewset-0.0.1.dist-info/RECORD
