Metadata-Version: 2.3
Name: django-excel-viewset
Version: 0.0.1
Summary: Django Excel ViewSet
License: Apache-2.0
Author: Sergey V. Elfimov
Author-email: elfimovserg@gmail.com
Requires-Python: >=3.11,<4.0
Classifier: Framework :: Django
Classifier: License :: OSI Approved :: Apache Software License
Classifier: Natural Language :: English
Classifier: Operating System :: OS Independent
Classifier: Programming Language :: Python
Classifier: Programming Language :: Python :: 3
Classifier: Programming Language :: Python :: 3.11
Classifier: Programming Language :: Python :: 3.12
Classifier: Programming Language :: Python :: 3.13
Classifier: Programming Language :: Python :: 3 :: Only
Requires-Dist: django (>=4.2,<6.0)
Requires-Dist: djangorestframework (>=3.11)
Requires-Dist: environs (>=9.3.1)
Requires-Dist: pillow (>=9.2)
Requires-Dist: pytz (>=2020.1)
Requires-Dist: xlsxwriter (>=1.3.6)
Project-URL: Repository, https://github.com/SergeiVElfimov/django-excel-viewset
